Workbook
Name NativeTimeline_Order_Date: #N/A
Name Slicer_Category: #N/A
Name Slicer_District: #N/A
Name Slicer_Order_Status: #N/A
Name Slicer_Payment_Method: #N/A
Name Slicer_Sales_Channel: #N/A

Sheet Ecommerce_Data
A1: Order_ID | B1: Customer_ID | C1: Order_Date | D1: City | E1: District | F1: Gender | G1: Customer_Age | H1: Age_Group | I1: Category | J1: Product | K1: Quantity | L1: Unit_Price_INR | M1: Discount | N1: Discount % | O1: Discount_Amount_INR | P1: Order_Value_INR | Q1: Shipping_Charge_INR | R1: Total_Amount_INR | S1: Payment_Method | T1: Sales_Channel | U1: Order_Status | V1: Delivery_Days | W1: Customer_Rating
A2: TNORD0001 | B2: TNCUST0060 | C2: 45674 | D2: Dindigul | E2: Dindigul | F2: Other | G2: 23 | H2: 56+ | I2: Electronics | J2: Smartphone | K2: 3 | L2: 32898 | M2: 20 | N2: =Table1[[#This Row],[Discount]]/100 -> 0.2 | O2: 19738.8 | P2: 78955.2 | Q2: 128 | R2: 79083.2 | S2: UPI | T2: Marketplace | U2: Delivered | V2: 1 | W2: 3.5
A3: TNORD0002 | B3: TNCUST0072 | C3: 46015 | D3: Tiruchirappalli | E3: Tiruchirappalli | F3: Male | G3: 39 | H3: 26-35 | I3: Sports | J3: Badminton Racket | K3: 4 | L3: 7521 | M3: 0 | N3: =Table1[[#This Row],[Discount]]/100 -> 0 | O3: 0 | P3: 30084 | Q3: 60 | R3: 30144 | S3: Debit Card | T3: Website | U3: Shipped | V3: 4
A4: TNORD0003 | B4: TNCUST0159 | C4: 45698 | D4: Coimbatore | E4: Coimbatore | F4: Female | G4: 36 | H4: 56+ | I4: Grocery | J4: Rice | K4: 3 | L4: 257 | M4: 20 | N4: =Table1[[#This Row],[Discount]]/100 -> 0.2 | O4: 154.2 | P4: 616.8 | Q4: 116 | R4: 732.8 | S4: Credit Card | T4: Marketplace | U4: Delivered | V4: 5 | W4: 5
A5: TNORD0004 | B5: TNCUST0172 | C5: 45847 | D5: Coimbatore | E5: Coimbatore | F5: Female | G5: 31 | H5: 18-25 | I5: Electronics | J5: Laptop | K5: 3 | L5: 11258 | M5: 25 | N5: =Table1[[#This Row],[Discount]]/100 -> 0.25 | O5: 8443.5 | P5: 25330.5 | Q5: 61 | R5: 25391.5 | S5: Net Banking | T5: Marketplace | U5: Processing
A6: TNORD0005 | B6: TNCUST0207 | C6: 45686 | D6: Madurai | E6: Madurai | F6: Female | G6: 20 | H6: 46-55 | I6: Beauty | J6: Shampoo | K6: 2 | L6: 1049 | M6: 10 | N6: =Table1[[#This Row],[Discount]]/100 -> 0.1 | O6: 209.8 | P6: 1888.2 | Q6: 218 | R6: 2106.2 | S6: Debit Card | T6: Website | U6: Processing
A7: TNORD0006 | B7: TNCUST0110 | C7: 45792 | D7: Tiruchirappalli | E7: Tiruchirappalli | F7: Other | G7: 55 | H7: 46-55 | I7: Beauty | J7: Moisturizer | K7: 2 | L7: 1234 | M7: 5 | N7: =Table1[[#This Row],[Discount]]/100 -> 0.05 | O7: 123.4 | P7: 2344.6 | Q7: 157 | R7: 2501.6 | S7: Debit Card | T7: Website | U7: Shipped | V7: 6
A8: TNORD0007 | B8: TNCUST0065 | C8: 45853 | D8: Madurai | E8: Madurai | F8: Other | G8: 47 | H8: 18-25 | I8: Beauty | J8: Sunscreen | K8: 1 | L8: 3394 | M8: 15 | N8: =Table1[[#This Row],[Discount]]/100 -> 0.15 | O8: 509.1 | P8: 2884.9 | Q8: 118 | R8: 3002.9 | S8: Wallet | T8: Marketplace | U8: Delivered | V8: 5 | W8: 4.5
A9: TNORD0008 | B9: TNCUST0130 | C9: 45792 | D9: Coimbatore | E9: Coimbatore | F9: Male | G9: 29 | H9: 36-45 | I9: Sports | J9: Badminton Racket | K9: 3 | L9: 4116 | M9: 0 | N9: =Table1[[#This Row],[Discount]]/100 -> 0 | O9: 0 | P9: 12348 | Q9: 244 | R9: 12592 | S9: Wallet | T9: Marketplace | U9: Returned
A10: TNORD0009 | B10: TNCUST0225 | C10: 45815 | D10: Thanjavur | E10: Thanjavur | F10: Other | G10: 21 | H10: 18-25 | I10: Fashion | J10: Kurta | K10: 3 | L10: 4818 | M10: 15 | N10: =Table1[[#This Row],[Discount]]/100 -> 0.15 | O10: 2168.1 | P10: 12285.9 | Q10: 112 | R10: 12397.9 | S10: UPI | T10: Marketplace | U10: Delivered | V10: 2 | W10: 3.5
A11: TNORD0010 | B11: TNCUST0183 | C11: 45766 | D11: Vellore | E11: Vellore | F11: Female | G11: 30 | H11: 46-55 | I11: Electronics | J11: Power Bank | K11: 2 | L11: 17628 | M11: 20 | N11: =Table1[[#This Row],[Discount]]/100 -> 0.2 | O11: 7051.2 | P11: 28204.8 | Q11: 128 | R11: 28332.8 | S11: Wallet | T11: Marketplace | U11: Cancelled
A12: TNORD0011 | B12: TNCUST0162 | C12: 45770 | D12: Tirunelveli | E12: Tirunelveli | F12: Male | G12: 22 | H12: 26-35 | I12: Grocery | J12: Tea | K12: 4 | L12: 342 | M12: 20 | N12: =Table1[[#This Row],[Discount]]/100 -> 0.2 | O12: 273.6 | P12: 1094.4 | Q12: 170 | R12: 1264.4 | S12: UPI | T12: Website | U12: Delivered | V12: 1 | W12: 5
A13: TNORD0012 | B13: TNCUST0201 | C13: 45953 | D13: Kanchipuram | E13: Kanchipuram | F13: Female | G13: 33 | H13: 46-55 | I13: Home & Kitchen | J13: Mixer Grinder | K13: 5 | L13: 8253 | M13: 25 | N13: =Table1[[#This Row],[Discount]]/100 -> 0.25 | O13: 10316.25 | P13: 30948.75 | Q13: 166 | R13: 31114.75 | S13: Credit Card | T13: Website | U13: Returned
A14: TNORD0013 | B14: TNCUST0050 | C14: 45831 | D14: Coimbatore | E14: Coimbatore | F14: Male | G14: 24 | H14: 56+ | I14: Sports | J14: Running Shoes | K14: 3 | L14: 5753 | M14: 25 | N14: =Table1[[#This Row],[Discount]]/100 -> 0.25 | O14: 4314.75 | P14: 12944.25 | Q14: 123 | R14: 13067.25 | S14: Cash on Delivery | T14: Website | U14: Delivered | V14: 7 | W14: 3.5
A15: TNORD0014 | B15: TNCUST0043 | C15: 45665 | D15: Erode | E15: Erode | F15: Female | G15: 33 | H15: 46-55 | I15: Fashion | J15: T-Shirt | K15: 4 | L15: 1017 | M15: 25 | N15: =Table1[[#This Row],[Discount]]/100 -> 0.25 | O15: 1017 | P15: 3051 | Q15: 234 | R15: 3285 | S15: Cash on Delivery | T15: Website | U15: Returned
A16: TNORD0015 | B16: TNCUST0049 | C16: 45942 | D16: Kanchipuram | E16: Kanchipuram | F16: Female | G16: 49 | H16: 26-35 | I16: Grocery | J16: Rice | K16: 2 | L16: 1166 | M16: 15 | N16: =Table1[[#This Row],[Discount]]/100 -> 0.15 | O16: 349.8 | P16: 1982.2 | Q16: 198 | R16: 2180.2 | S16: UPI | T16: Marketplace | U16: Delivered | V16: 6 | W16: 3.5
A17: TNORD0016 | B17: TNCUST0153 | C17: 45699 | D17: Hosur | E17: Krishnagiri | F17: Male | G17: 29 | H17: 26-35 | I17: Beauty | J17: Face Wash | K17: 3 | L17: 2209 | M17: 20 | N17: =Table1[[#This Row],[Discount]]/100 -> 0.2 | O17: 1325.4 | P17: 5301.6 | Q17: 150 | R17: 5451.6 | S17: Cash on Delivery | T17: Website | U17: Delivered | V17: 7 | W17: 3
A18: TNORD0017 | B18: TNCUST0068 | C18: 45762 | D18: Karur | E18: Karur | F18: Female | G18: 38 | H18: 26-35 | I18: Beauty | J18: Shampoo | K18: 5 | L18: 2842 | M18: 20 | N18: =Table1[[#This Row],[Discount]]/100 -> 0.2 | O18: 2842 | P18: 11368 | Q18: 86 | R18: 11454 | S18: Wallet | T18: Marketplace | U18: Delivered | V18: 6 | W18: 3.5
A19: TNORD0018 | B19: TNCUST0073 | C19: 45836 | D19: Salem | E19: Salem | F19: Male | G19: 33 | H19: 46-55 | I19: Grocery | J19: Spices | K19: 1 | L19: 489 | M19: 5 | N19: =Table1[[#This Row],[Discount]]/100 -> 0.05 | O19: 24.45 | P19: 464.55 | Q19: 53 | R19: 517.55 | S19: Net Banking | T19: Marketplace | U19: Delivered | V19: 1 | W19: 4
A20: TNORD0019 | B20: TNCUST0054 | C20: 45797 | D20: Salem | E20: Salem | F20: Other | G20: 56 | H20: 36-45 | I20: Beauty | J20: Perfume | K20: 1 | L20: 1233 | M20: 0 | N20: =Table1[[#This Row],[Discount]]/100 -> 0 | O20: 0 | P20: 1233 | Q20: 59 | R20: 1292 | S20: Credit Card | T20: Marketplace | U20: Shipped | V20: 3
A21: TNORD0020 | B21: TNCUST0190 | C21: 45724 | D21: Dindigul | E21: Dindigul | F21: Female | G21: 34 | H21: 56+ | I21: Home & Kitchen | J21: Storage Box | K21: 4 | L21: 1812 | M21: 0 | N21: =Table1[[#This Row],[Discount]]/100 -> 0 | O21: 0 | P21: 7248 | Q21: 217 | R21: 7465 | S21: Wallet | T21: Mobile App | U21: Delivered | V21: 6 | W21: 3.5
A22: TNORD0021 | B22: TNCUST0054 | C22: 45815 | D22: Thoothukudi | E22: Thoothukudi | F22: Other | G22: 20 | H22: 26-35 | I22: Electronics | J22: Smartphone | K22: 1 | L22: 20336 | M22: 5 | N22: =Table1[[#This Row],[Discount]]/100 -> 0.05 | O22: 1016.8 | P22: 19319.2 | Q22: 30 | R22: 19349.2 | S22: Wallet | T22: Website | U22: Delivered | V22: 3 | W22: 4
A23: TNORD0022 | B23: TNCUST0208 | C23: 45868 | D23: Tirunelveli | E23: Tirunelveli | F23: Male | G23: 60 | H23: 36-45 | I23: Beauty | J23: Sunscreen | K23: 5 | L23: 3760 | M23: 0 | N23: =Table1[[#This Row],[Discount]]/100 -> 0 | O23: 0 | P23: 18800 | Q23: 105 | R23: 18905 | S23: Credit Card | T23: Marketplace | U23: Delivered | V23: 7 | W23: 5
A24: TNORD0023 | B24: TNCUST0222 | C24: 45756 | D24: Coimbatore | E24: Coimbatore | F24: Male | G24: 39 | H24: 36-45 | I24: Grocery | J24: Rice | K24: 4 | L24: 1512 | M24: 5 | N24: =Table1[[#This Row],[Discount]]/100 -> 0.05 | O24: 302.4 | P24: 5745.6 | Q24: 188 | R24: 5933.6 | S24: Debit Card | T24: Marketplace | U24: Delivered | V24: 4 | W24: 4
A25: TNORD0024 | B25: TNCUST0156 | C25: 45834 | D25: Thoothukudi | E25: Thoothukudi | F25: Other | G25: 38 | H25: 18-25 | I25: Grocery | J25: Tea | K25: 3 | L25: 811 | M25: 0 | N25: =Table1[[#This Row],[Discount]]/100 -> 0 | O25: 0 | P25: 2433 | Q25: 131 | R25: 2564 | S25: Cash on Delivery | T25: Marketplace | U25: Delivered | V25: 6 | W25: 4
A26: TNORD0025 | B26: TNCUST0218 | C26: 45977 | D26: Tiruchirappalli | E26: Tiruchirappalli | F26: Male | G26: 60 | H26: 36-45 | I26: Home & Kitchen | J26: Mixer Grinder | K26: 4 | L26: 9121 | M26: 0 | N26: =Table1[[#This Row],[Discount]]/100 -> 0 | O26: 0 | P26: 36484 | Q26: 104 | R26: 36588 | S26: Net Banking | T26: Mobile App | U26: Returned
A27: TNORD0026 | B27: TNCUST0104 | C27: 45973 | D27: Dindigul | E27: Dindigul | F27: Other | G27: 37 | H27: 18-25 | I27: Grocery | J27: Spices | K27: 4 | L27: 865 | M27: 15 | N27: =Table1[[#This Row],[Discount]]/100 -> 0.15 | O27: 519 | P27: 2941 | Q27: 64 | R27: 3005 | S27: Debit Card | T27: Mobile App | U27: Shipped | V27: 5
A28: TNORD0027 | B28: TNCUST0132 | C28: 45744 | D28: Tiruchirappalli | E28: Tiruchirappalli | F28: Other | G28: 23 | H28: 56+ | I28: Grocery | J28: Tea | K28: 5 | L28: 1891 | M28: 20 | N28: =Table1[[#This Row],[Discount]]/100 -> 0.2 | O28: 1891 | P28: 7564 | Q28: 250 | R28: 7814 | S28: Debit Card | T28: Website | U28: Delivered | V28: 6 | W28: 4
A29: TNORD0028 | B29: TNCUST0148 | C29: 45891 | D29: Kanchipuram | E29: Kanchipuram | F29: Male | G29: 58 | H29: 46-55 | I29: Fashion | J29: T-Shirt | K29: 2 | L29: 1607 | M29: 20 | N29: =Table1[[#This Row],[Discount]]/100 -> 0.2 | O29: 642.8 | P29: 2571.2 | Q29: 38 | R29: 2609.2 | S29: Cash on Delivery | T29: Mobile App | U29: Processing
A30: TNORD0029 | B30: TNCUST0171 | C30: 45720 | D30: Tiruchirappalli | E30: Tiruchirappalli | F30: Other | G30: 26 | H30: 56+ | I30: Fashion | J30: Saree | K30: 1 | L30: 2192 | M30: 20 | N30: =Table1[[#This Row],[Discount]]/100 -> 0.2 | O30: 438.4 | P30: 1753.6 | Q30: 237 | R30: 1990.6 | S30: Net Banking | T30: Mobile App | U30: Delivered | V30: 4 | W30: 4
A31: TNORD0030 | B31: TNCUST0197 | C31: 45784 | D31: Nagercoil | E31: Kanyakumari | F31: Other | G31: 58 | H31: 46-55 | I31: Grocery | J31: Tea | K31: 5 | L31: 731 | M31: 15 | N31: =Table1[[#This Row],[Discount]]/100 -> 0.15 | O31: 548.25 | P31: 3106.75 | Q31: 212 | R31: 3318.75 | S31: Wallet | T31: Website | U31: Delivered | V31: 7 | W31: 4
A32: TNORD0031 | B32: TNCUST0055 | C32: 45854 | D32: Salem | E32: Salem | F32: Male | G32: 27 | H32: 46-55 | I32: Grocery | J32: Rice | K32: 3 | L32: 1389 | M32: 0 | N32: =Table1[[#This Row],[Discount]]/100 -> 0 | O32: 0 | P32: 4167 | Q32: 79 | R32: 4246 | S32: Cash on Delivery | T32: Mobile App | U32: Delivered | V32: 6 | W32: 5
A33: TNORD0032 | B33: TNCUST0138 | C33: 45838 | D33: Thoothukudi | E33: Thoothukudi | F33: Other | G33: 42 | H33: 56+ | I33: Grocery | J33: Snacks | K33: 1 | L33: 2472 | M33: 20 | N33: =Table1[[#This Row],[Discount]]/100 -> 0.2 | O33: 494.4 | P33: 1977.6 | Q33: 21 | R33: 1998.6 | S33: Net Banking | T33: Website | U33: Delivered | V33: 3 | W33: 4
A34: TNORD0033 | B34: TNCUST0137 | C34: 45897 | D34: Vellore | E34: Vellore | F34: Male | G34: 57 | H34: 46-55 | I34: Fashion | J34: T-Shirt | K34: 4 | L34: 637 | M34: 15 | N34: =Table1[[#This Row],[Discount]]/100 -> 0.15 | O34: 382.2 | P34: 2165.8 | Q34: 235 | R34: 2400.8 | S34: Net Banking | T34: Marketplace | U34: Shipped | V34: 2
A35: TNORD0034 | B35: TNCUST0193 | C35: 45830 | D35: Dindigul | E35: Dindigul | F35: Female | G35: 42 | H35: 36-45 | I35: Electronics | J35: Smartphone | K35: 4 | L35: 18586 | M35: 10 | N35: =Table1[[#This Row],[Discount]]/100 -> 0.1 | O35: 7434.4 | P35: 66909.6 | Q35: 103 | R35: 67012.6 | S35: UPI | T35: Mobile App | U35: Delivered | V35: 7 | W35: 4
A36: TNORD0035 | B36: TNCUST0122 | C36: 45976 | D36: Chennai | E36: Chennai | F36: Other | G36: 33 | H36: 18-25 | I36: Sports | J36: Badminton Racket | K36: 1 | L36: 654 | M36: 5 | N36: =Table1[[#This Row],[Discount]]/100 -> 0.05 | O36: 32.7 | P36: 621.3 | Q36: 25 | R36: 646.3 | S36: Net Banking | T36: Website | U36: Delivered | V36: 2 | W36: 3.5
A37: TNORD0036 | B37: TNCUST0242 | C37: 45952 | D37: Vellore | E37: Vellore | F37: Other | G37: 42 | H37: 26-35 | I37: Sports | J37: Yoga Mat | K37: 3 | L37: 1285 | M37: 20 | N37: =Table1[[#This Row],[Discount]]/100 -> 0.2 | O37: 771 | P37: 3084 | Q37: 99 | R37: 3183 | S37: UPI | T37: Marketplace | U37: Delivered | V37: 6 | W37: 4
A38: TNORD0037 | B38: TNCUST0088 | C38: 45847 | D38: Hosur | E38: Krishnagiri | F38: Male | G38: 50 | H38: 46-55 | I38: Sports | J38: Football | K38: 1 | L38: 736 | M38: 10 | N38: =Table1[[#This Row],[Discount]]/100 -> 0.1 | O38: 73.6 | P38: 662.4 | Q38: 189 | R38: 851.4 | S38: Cash on Delivery | T38: Website | U38: Delivered | V38: 1 | W38: 5
A39: TNORD0038 | B39: TNCUST0069 | C39: 45881 | D39: Erode | E39: Erode | F39: Female | G39: 55 | H39: 26-35 | I39: Home & Kitchen | J39: Water Bottle | K39: 2 | L39: 8848 | M39: 20 | N39: =Table1[[#This Row],[Discount]]/100 -> 0.2 | O39: 3539.2 | P39: 14156.8 | Q39: 139 | R39: 14295.8 | S39: UPI | T39: Mobile App | U39: Processing
A40: TNORD0039 | B40: TNCUST0180 | C40: 45790 | D40: Karur | E40: Karur | F40: Female | G40: 35 | H40: 56+ | I40: Grocery | J40: Cooking Oil | K40: 4 | L40: 2104 | M40: 5 | N40: =Table1[[#This Row],[Discount]]/100 -> 0.05 | O40: 420.8 | P40: 7995.2 | Q40: 110 | R40: 8105.2 | S40: UPI | T40: Marketplace | U40: Delivered | V40: 3 | W40: 4.5
A41: TNORD0040 | B41: TNCUST0178 | C41: 45705 | D41: Tiruchirappalli | E41: Tiruchirappalli | F41: Male | G41: 32 | H41: 36-45 | I41: Electronics | J41: Laptop | K41: 4 | L41: 64838 | M41: 15 | N41: =Table1[[#This Row],[Discount]]/100 -> 0.15 | O41: 38902.8 | P41: 220449.2 | Q41: 24 | R41: 220473.2 | S41: Wallet | T41: Marketplace | U41: Delivered | V41: 3 | W41: 4
A42: TNORD0041 | B42: TNCUST0031 | C42: 45776 | D42: Tirunelveli | E42: Tirunelveli | F42: Other | G42: 30 | H42: 56+ | I42: Grocery | J42: Tea | K42: 5 | L42: 1434 | M42: 15 | N42: =Table1[[#This Row],[Discount]]/100 -> 0.15 | O42: 1075.5 | P42: 6094.5 | Q42: 84 | R42: 6178.5 | S42: Wallet | T42: Website | U42: Delivered | V42: 1 | W42: 4
A43: TNORD0042 | B43: TNCUST0071 | C43: 45812 | D43: Tiruchirappalli | E43: Tiruchirappalli | F43: Male | G43: 52 | H43: 18-25 | I43: Fashion | J43: Jeans | K43: 3 | L43: 5288 | M43: 10 | N43: =Table1[[#This Row],[Discount]]/100 -> 0.1 | O43: 1586.4 | P43: 14277.6 | Q43: 65 | R43: 14342.6 | S43: Net Banking | T43: Mobile App | U43: Delivered | V43: 1 | W43: 3.5
A44: TNORD0043 | B44: TNCUST0211 | C44: 45787 | D44: Hosur | E44: Krishnagiri | F44: Male | G44: 48 | H44: 46-55 | I44: Fashion | J44: Jeans | K44: 1 | L44: 5102 | M44: 10 | N44: =Table1[[#This Row],[Discount]]/100 -> 0.1 | O44: 510.2 | P44: 4591.8 | Q44: 33 | R44: 4624.8 | S44: Cash on Delivery | T44: Website | U44: Delivered | V44: 7 | W44: 3
A45: TNORD0044 | B45: TNCUST0058 | C45: 45963 | D45: Thanjavur | E45: Thanjavur | F45: Other | G45: 57 | H45: 46-55 | I45: Sports | J45: Cricket Bat | K45: 2 | L45: 1370 | M45: 20 | N45: =Table1[[#This Row],[Discount]]/100 -> 0.2 | O45: 548 | P45: 2192 | Q45: 175 | R45: 2367 | S45: Cash on Delivery | T45: Mobile App | U45: Processing
A46: TNORD0045 | B46: TNCUST0020 | C46: 45780 | D46: Salem | E46: Salem | F46: Male | G46: 53 | H46: 18-25 | I46: Beauty | J46: Sunscreen | K46: 3 | L46: 2712 | M46: 10 | N46: =Table1[[#This Row],[Discount]]/100 -> 0.1 | O46: 813.6 | P46: 7322.4 | Q46: 60 | R46: 7382.4 | S46: Cash on Delivery | T46: Mobile App | U46: Shipped | V46: 2
A47: TNORD0046 | B47: TNCUST0170 | C47: 45793 | D47: Hosur | E47: Krishnagiri | F47: Male | G47: 58 | H47: 46-55 | I47: Beauty | J47: Sunscreen | K47: 3 | L47: 3029 | M47: 15 | N47: =Table1[[#This Row],[Discount]]/100 -> 0.15 | O47: 1363.05 | P47: 7723.95 | Q47: 79 | R47: 7802.95 | S47: UPI | T47: Marketplace | U47: Delivered | V47: 7 | W47: 4.5
A48: TNORD0047 | B48: TNCUST0120 | C48: 45805 | D48: Tiruchirappalli | E48: Tiruchirappalli | F48: Other | G48: 25 | H48: 36-45 | I48: Sports | J48: Football | K48: 3 | L48: 2919 | M48: 20 | N48: =Table1[[#This Row],[Discount]]/100 -> 0.2 | O48: 1751.4 | P48: 7005.6 | Q48: 165 | R48: 7170.6 | S48: Wallet | T48: Mobile App | U48: Shipped | V48: 4
A49: TNORD0048 | B49: TNCUST0244 | C49: 45775 | D49: Salem | E49: Salem | F49: Male | G49: 54 | H49: 36-45 | I49: Beauty | J49: Perfume | K49: 4 | L49: 3158 | M49: 20 | N49: =Table1[[#This Row],[Discount]]/100 -> 0.2 | O49: 2526.4 | P49: 10105.6 | Q49: 43 | R49: 10148.6 | S49: Net Banking | T49: Website | U49: Delivered | V49: 6 | W49: 4.5
A50: TNORD0049 | B50: TNCUST0083 | C50: 45836 | D50: Nagercoil | E50: Kanyakumari | F50: Other | G50: 39 | H50: 18-25 | I50: Fashion | J50: Jeans | K50: 5 | L50: 2678 | M50: 15 | N50: =Table1[[#This Row],[Discount]]/100 -> 0.15 | O50: 2008.5 | P50: 11381.5 | Q50: 140 | R50: 11521.5 | S50: Credit Card | T50: Mobile App | U50: Returned
A51: TNORD0050 | B51: TNCUST0169 | C51: 45864 | D51: Erode | E51: Erode | F51: Other | G51: 50 | H51: 46-55 | I51: Sports | J51: Running Shoes | K51: 3 | L51: 2976 | M51: 10 | N51: =Table1[[#This Row],[Discount]]/100 -> 0.1 | O51: 892.8 | P51: 8035.2 | Q51: 217 | R51: 8252.2 | S51: Cash on Delivery | T51: Website | U51: Delivered | V51: 7 | W51: 3
A52: TNORD0051 | B52: TNCUST0008 | C52: 45882 | D52: Tiruchirappalli | E52: Tiruchirappalli | F52: Other | G52: 49 | H52: 56+ | I52: Beauty | J52: Moisturizer | K52: 5 | L52: 983 | M52: 20 | N52: =Table1[[#This Row],[Discount]]/100 -> 0.2 | O52: 983 | P52: 3932 | Q52: 93 | R52: 4025 | S52: Credit Card | T52: Marketplace | U52: Delivered | V52: 6 | W52: 3
A53: TNORD0052 | B53: TNCUST0239 | C53: 45989 | D53: Madurai | E53: Madurai | F53: Other | G53: 27 | H53: 36-45 | I53: Home & Kitchen | J53: Storage Box | K53: 1 | L53: 1827 | M53: 0 | N53: =Table1[[#This Row],[Discount]]/100 -> 0 | O53: 0 | P53: 1827 | Q53: 50 | R53: 1877 | S53: Net Banking | T53: Marketplace | U53: Delivered | V53: 7 | W53: 4
A54: TNORD0053 | B54: TNCUST0198 | C54: 45727 | D54: Salem | E54: Salem | F54: Female | G54: 22 | H54: 36-45 | I54: Grocery | J54: Snacks | K54: 4 | L54: 672 | M54: 20 | N54: =Table1[[#This Row],[Discount]]/100 -> 0.2 | O54: 537.6 | P54: 2150.4 | Q54: 245 | R54: 2395.4 | S54: Net Banking | T54: Mobile App | U54: Delivered | V54: 7 | W54: 4
A55: TNORD0054 | B55: TNCUST0179 | C55: 45851 | D55: Kanchipuram | E55: Kanchipuram | F55: Male | G55: 38 | H55: 56+ | I55: Electronics | J55: Headphones | K55: 3 | L55: 64978 | M55: 10 | N55: =Table1[[#This Row],[Discount]]/100 -> 0.1 | O55: 19493.4 | P55: 175440.6 | Q55: 159 | R55: 175599.6 | S55: Cash on Delivery | T55: Website | U55: Delivered | V55: 4 | W55: 3.5
A56: TNORD0055 | B56: TNCUST0026 | C56: 45827 | D56: Kanchipuram | E56: Kanchipuram | F56: Other | G56: 24 | H56: 46-55 | I56: Grocery | J56: Rice | K56: 3 | L56: 703 | M56: 5 | N56: =Table1[[#This Row],[Discount]]/100 -> 0.05 | O56: 105.45 | P56: 2003.55 | Q56: 171 | R56: 2174.55 | S56: UPI | T56: Marketplace | U56: Delivered | V56: 7 | W56: 4
A57: TNORD0056 | B57: TNCUST0161 | C57: 45931 | D57: Madurai | E57: Madurai | F57: Other | G57: 38 | H57: 46-55 | I57: Grocery | J57: Cooking Oil | K57: 1 | L57: 1708 | M57: 10 | N57: =Table1[[#This Row],[Discount]]/100 -> 0.1 | O57: 170.8 | P57: 1537.2 | Q57: 239 | R57: 1776.2 | S57: Net Banking | T57: Website | U57: Processing
A58: TNORD0057 | B58: TNCUST0232 | C58: 45743 | D58: Thanjavur | E58: Thanjavur | F58: Male | G58: 37 | H58: 18-25 | I58: Electronics | J58: Laptop | K58: 3 | L58: 30617 | M58: 25 | N58: =Table1[[#This Row],[Discount]]/100 -> 0.25 | O58: 22962.75 | P58: 68888.25 | Q58: 133 | R58: 69021.25 | S58: Debit Card | T58: Website | U58: Cancelled
A59: TNORD0058 | B59: TNCUST0175 | C59: 45970 | D59: Salem | E59: Salem | F59: Male | G59: 42 | H59: 46-55 | I59: Home & Kitchen | J59: Bedsheet | K59: 4 | L59: 9002 | M59: 5 | N59: =Table1[[#This Row],[Discount]]/100 -> 0.05 | O59: 1800.4 | P59: 34207.6 | Q59: 40 | R59: 34247.6 | S59: Net Banking | T59: Website | U59: Delivered | V59: 7 | W59: 4.5
A60: TNORD0059 | B60: TNCUST0164 | C60: 45884 | D60: Tiruchirappalli | E60: Tiruchirappalli | F60: Female | G60: 55 | H60: 36-45 | I60: Grocery | J60: Spices | K60: 4 | L60: 1985 | M60: 25 | N60: =Table1[[#This Row],[Discount]]/100 -> 0.25 | O60: 1985 | P60: 5955 | Q60: 38 | R60: 5993 | S60: Cash on Delivery | T60: Mobile App | U60: Delivered | V60: 3 | W60: 4
A61: TNORD0060 | B61: TNCUST0145 | C61: 45995 | D61: Tiruchirappalli | E61: Tiruchirappalli | F61: Other | G61: 35 | H61: 18-25 | I61: Grocery | J61: Snacks | K61: 1 | L61: 1550 | M61: 25 | N61: =Table1[[#This Row],[Discount]]/100 -> 0.25 | O61: 387.5 | P61: 1162.5 | Q61: 232 | R61: 1394.5 | S61: Net Banking | T61: Marketplace | U61: Delivered | V61: 4 | W61: 3
A62: TNORD0061 | B62: TNCUST0232 | C62: 45728 | D62: Vellore | E62: Vellore | F62: Other | G62: 24 | H62: 18-25 | I62: Home & Kitchen | J62: Cookware Set | K62: 5 | L62: 3415 | M62: 25 | N62: =Table1[[#This Row],[Discount]]/100 -> 0.25 | O62: 4268.75 | P62: 12806.25 | Q62: 194 | R62: 13000.25 | S62: Debit Card | T62: Mobile App | U62: Processing
A63: TNORD0062 | B63: TNCUST0234 | C63: 45845 | D63: Chennai | E63: Chennai | F63: Female | G63: 50 | H63: 26-35 | I63: Beauty | J63: Moisturizer | K63: 2 | L63: 869 | M63: 5 | N63: =Table1[[#This Row],[Discount]]/100 -> 0.05 | O63: 86.9 | P63: 1651.1 | Q63: 244 | R63: 1895.1 | S63: Debit Card | T63: Mobile App | U63: Processing
A64: TNORD0063 | B64: TNCUST0203 | C64: 45943 | D64: Nagercoil | E64: Kanyakumari | F64: Female | G64: 23 | H64: 18-25 | I64: Home & Kitchen | J64: Bedsheet | K64: 1 | L64: 2606 | M64: 25 | N64: =Table1[[#This Row],[Discount]]/100 -> 0.25 | O64: 651.5 | P64: 1954.5 | Q64: 121 | R64: 2075.5 | S64: Debit Card | T64: Marketplace | U64: Shipped | V64: 3
A65: TNORD0064 | B65: TNCUST0166 | C65: 45945 | D65: Coimbatore | E65: Coimbatore | F65: Male | G65: 57 | H65: 46-55 | I65: Grocery | J65: Spices | K65: 3 | L65: 523 | M65: 15 | N65: =Table1[[#This Row],[Discount]]/100 -> 0.15 | O65: 235.35 | P65: 1333.65 | Q65: 246 | R65: 1579.65 | S65: Wallet | T65: Mobile App | U65: Delivered | V65: 3 | W65: 3.5
A66: TNORD0065 | B66: TNCUST0172 | C66: 45856 | D66: Dindigul | E66: Dindigul | F66: Other | G66: 41 | H66: 56+ | I66: Grocery | J66: Rice | K66: 2 | L66: 2097 | M66: 5 | N66: =Table1[[#This Row],[Discount]]/100 -> 0.05 | O66: 209.7 | P66: 3984.3 | Q66: 54 | R66: 4038.3 | S66: Cash on Delivery | T66: Marketplace | U66: Cancelled
A67: TNORD0066 | B67: TNCUST0176 | C67: 45778 | D67: Hosur | E67: Krishnagiri | F67: Female | G67: 41 | H67: 56+ | I67: Sports | J67: Football | K67: 4 | L67: 6054 | M67: 10 | N67: =Table1[[#This Row],[Discount]]/100 -> 0.1 | O67: 2421.6 | P67: 21794.4 | Q67: 133 | R67: 21927.4 | S67: Wallet | T67: Mobile App | U67: Delivered | V67: 7 | W67: 3
A68: TNORD0067 | B68: TNCUST0202 | C68: 45828 | D68: Chennai | E68: Chennai | F68: Other | G68: 26 | H68: 26-35 | I68: Grocery | J68: Spices | K68: 2 | L68: 948 | M68: 20 | N68: =Table1[[#This Row],[Discount]]/100 -> 0.2 | O68: 379.2 | P68: 1516.8 | Q68: 32 | R68: 1548.8 | S68: UPI | T68: Marketplace | U68: Returned
A69: TNORD0068 | B69: TNCUST0034 | C69: 45747 | D69: Tiruchirappalli | E69: Tiruchirappalli | F69: Male | G69: 60 | H69: 36-45 | I69: Beauty | J69: Shampoo | K69: 2 | L69: 3666 | M69: 5 | N69: =Table1[[#This Row],[Discount]]/100 -> 0.05 | O69: 366.6 | P69: 6965.4 | Q69: 224 | R69: 7189.4 | S69: Credit Card | T69: Marketplace | U69: Delivered | V69: 1 | W69: 3
A70: TNORD0069 | B70: TNCUST0116 | C70: 45843 | D70: Tirunelveli | E70: Tirunelveli | F70: Other | G70: 55 | H70: 26-35 | I70: Electronics | J70: Laptop | K70: 3 | L70: 7668 | M70: 0 | N70: =Table1[[#This Row],[Discount]]/100 -> 0 | O70: 0 | P70: 23004 | Q70: 219 | R70: 23223 | S70: Net Banking | T70: Website | U70: Delivered | V70: 5 | W70: 3
A71: TNORD0070 | B71: TNCUST0231 | C71: 45909 | D71: Hosur | E71: Krishnagiri | F71: Male | G71: 46 | H71: 36-45 | I71: Sports | J71: Badminton Racket | K71: 3 | L71: 7341 | M71: 15 | N71: =Table1[[#This Row],[Discount]]/100 -> 0.15 | O71: 3303.45 | P71: 18719.55 | Q71: 47 | R71: 18766.55 | S71: Net Banking | T71: Website | U71: Delivered | V71: 6 | W71: 3
A72: TNORD0071 | B72: TNCUST0225 | C72: 46017 | D72: Coimbatore | E72: Coimbatore | F72: Other | G72: 59 | H72: 26-35 | I72: Fashion | J72: T-Shirt | K72: 5 | L72: 3063 | M72: 20 | N72: =Table1[[#This Row],[Discount]]/100 -> 0.2 | O72: 3063 | P72: 12252 | Q72: 45 | R72: 12297 | S72: Cash on Delivery | T72: Mobile App | U72: Delivered | V72: 1 | W72: 5
A73: TNORD0072 | B73: TNCUST0018 | C73: 45736 | D73: Karur | E73: Karur | F73: Male | G73: 48 | H73: 18-25 | I73: Fashion | J73: Jeans | K73: 3 | L73: 3666 | M73: 10 | N73: =Table1[[#This Row],[Discount]]/100 -> 0.1 | O73: 1099.8 | P73: 9898.2 | Q73: 115 | R73: 10013.2 | S73: UPI | T73: Mobile App | U73: Shipped | V73: 6
A74: TNORD0073 | B74: TNCUST0014 | C74: 45998 | D74: Coimbatore | E74: Coimbatore | F74: Female | G74: 45 | H74: 56+ | I74: Sports | J74: Yoga Mat | K74: 2 | L74: 3100 | M74: 25 | N74: =Table1[[#This Row],[Discount]]/100 -> 0.25 | O74: 1550 | P74: 4650 | Q74: 110 | R74: 4760 | S74: Debit Card | T74: Mobile App | U74: Delivered | V74: 7 | W74: 5
A75: TNORD0074 | B75: TNCUST0147 | C75: 45716 | D75: Coimbatore | E75: Coimbatore | F75: Male | G75: 35 | H75: 46-55 | I75: Beauty | J75: Perfume | K75: 2 | L75: 3620 | M75: 10 | N75: =Table1[[#This Row],[Discount]]/100 -> 0.1 | O75: 724 | P75: 6516 | Q75: 114 | R75: 6630 | S75: Net Banking | T75: Marketplace | U75: Processing
A76: TNORD0075 | B76: TNCUST0145 | C76: 45661 | D76: Thanjavur | E76: Thanjavur | F76: Other | G76: 27 | H76: 46-55 | I76: Sports | J76: Badminton Racket | K76: 1 | L76: 6645 | M76: 10 | N76: =Table1[[#This Row],[Discount]]/100 -> 0.1 | O76: 664.5 | P76: 5980.5 | Q76: 109 | R76: 6089.5 | S76: UPI | T76: Website | U76: Cancelled
A77: TNORD0076 | B77: TNCUST0022 | C77: 45824 | D77: Hosur | E77: Krishnagiri | F77: Male | G77: 54 | H77: 26-35 | I77: Sports | J77: Cricket Bat | K77: 1 | L77: 3192 | M77: 5 | N77: =Table1[[#This Row],[Discount]]/100 -> 0.05 | O77: 159.6 | P77: 3032.4 | Q77: 204 | R77: 3236.4 | S77: Credit Card | T77: Marketplace | U77: Delivered | V77: 7 | W77: 4.5
A78: TNORD0077 | B78: TNCUST0029 | C78: 45920 | D78: Chennai | E78: Chennai | F78: Female | G78: 40 | H78: 56+ | I78: Sports | J78: Cricket Bat | K78: 3 | L78: 4021 | M78: 15 | N78: =Table1[[#This Row],[Discount]]/100 -> 0.15 | O78: 1809.45 | P78: 10253.55 | Q78: 213 | R78: 10466.55 | S78: Cash on Delivery | T78: Marketplace | U78: Delivered | V78: 1 | W78: 4
A79: TNORD0078 | B79: TNCUST0031 | C79: 45788 | D79: Dindigul | E79: Dindigul | F79: Male | G79: 38 | H79: 46-55 | I79: Home & Kitchen | J79: Mixer Grinder | K79: 2 | L79: 1197 | M79: 5 | N79: =Table1[[#This Row],[Discount]]/100 -> 0.05 | O79: 119.7 | P79: 2274.3 | Q79: 215 | R79: 2489.3 | S79: Wallet | T79: Mobile App | U79: Processing
A80: TNORD0079 | B80: TNCUST0110 | C80: 45893 | D80: Madurai | E80: Madurai | F80: Other | G80: 38 | H80: 46-55 | I80: Fashion | J80: Jeans | K80: 5 | L80: 4498 | M80: 25 | N80: =Table1[[#This Row],[Discount]]/100 -> 0.25 | O80: 5622.5 | P80: 16867.5 | Q80: 24 | R80: 16891.5 | S80: Wallet | T80: Marketplace | U80: Delivered | V80: 1 | W80: 4.5
A81: TNORD0080 | B81: TNCUST0103 | C81: 45712 | D81: Erode | E81: Erode | F81: Other | G81: 45 | H81: 18-25 | I81: Home & Kitchen | J81: Mixer Grinder | K81: 4 | L81: 3115 | M81: 10 | N81: =Table1[[#This Row],[Discount]]/100 -> 0.1 | O81: 1246 | P81: 11214 | Q81: 236 | R81: 11450 | S81: Cash on Delivery | T81: Mobile App | U81: Delivered | V81: 2 | W81: 4.5
A82: TNORD0081 | B82: TNCUST0209 | C82: 45837 | D82: Hosur | E82: Krishnagiri | F82: Male | G82: 59 | H82: 26-35 | I82: Home & Kitchen | J82: Cookware Set | K82: 3 | L82: 8663 | M82: 5 | N82: =Table1[[#This Row],[Discount]]/100 -> 0.05 | O82: 1299.45 | P82: 24689.55 | Q82: 109 | R82: 24798.55 | S82: UPI | T82: Website | U82: Cancelled
A83: TNORD0082 | B83: TNCUST0163 | C83: 45954 | D83: Salem | E83: Salem | F83: Other | G83: 54 | H83: 36-45 | I83: Fashion | J83: Kurta | K83: 5 | L83: 5769 | M83: 15 | N83: =Table1[[#This Row],[Discount]]/100 -> 0.15 | O83: 4326.75 | P83: 24518.25 | Q83: 164 | R83: 24682.25 | S83: Wallet | T83: Mobile App | U83: Delivered | V83: 4 | W83: 5
A84: TNORD0083 | B84: TNCUST0095 | C84: 45894 | D84: Madurai | E84: Madurai | F84: Female | G84: 20 | H84: 18-25 | I84: Grocery | J84: Rice | K84: 4 | L84: 1205 | M84: 10 | N84: =Table1[[#This Row],[Discount]]/100 -> 0.1 | O84: 482 | P84: 4338 | Q84: 99 | R84: 4437 | S84: Wallet | T84: Website | U84: Delivered | V84: 4 | W84: 3
A85: TNORD0084 | B85: TNCUST0039 | C85: 45967 | D85: Thanjavur | E85: Thanjavur | F85: Male | G85: 50 | H85: 46-55 | I85: Beauty | J85: Perfume | K85: 4 | L85: 1992 | M85: 20 | N85: =Table1[[#This Row],[Discount]]/100 -> 0.2 | O85: 1593.6 | P85: 6374.4 | Q85: 102 | R85: 6476.4 | S85: UPI | T85: Mobile App | U85: Shipped | V85: 4
A86: TNORD0085 | B86: TNCUST0174 | C86: 45802 | D86: Hosur | E86: Krishnagiri | F86: Other | G86: 44 | H86: 18-25 | I86: Electronics | J86: Power Bank | K86: 2 | L86: 5930 | M86: 20 | N86: =Table1[[#This Row],[Discount]]/100 -> 0.2 | O86: 2372 | P86: 9488 | Q86: 115 | R86: 9603 | S86: Wallet | T86: Marketplace | U86: Delivered | V86: 4 | W86: 4
A87: TNORD0086 | B87: TNCUST0150 | C87: 45734 | D87: Tirunelveli | E87: Tirunelveli | F87: Other | G87: 23 | H87: 26-35 | I87: Electronics | J87: Headphones | K87: 1 | L87: 73933 | M87: 25 | N87: =Table1[[#This Row],[Discount]]/100 -> 0.25 | O87: 18483.25 | P87: 55449.75 | Q87: 174 | R87: 55623.75 | S87: Debit Card | T87: Mobile App | U87: Returned
A88: TNORD0087 | B88: TNCUST0024 | C88: 46017 | D88: Dindigul | E88: Dindigul | F88: Other | G88: 51 | H88: 46-55 | I88: Sports | J88: Running Shoes | K88: 2 | L88: 6885 | M88: 10 | N88: =Table1[[#This Row],[Discount]]/100 -> 0.1 | O88: 1377 | P88: 12393 | Q88: 191 | R88: 12584 | S88: Net Banking | T88: Mobile App | U88: Processing
A89: TNORD0088 | B89: TNCUST0227 | C89: 45709 | D89: Chennai | E89: Chennai | F89: Other | G89: 52 | H89: 18-25 | I89: Home & Kitchen | J89: Bedsheet | K89: 2 | L89: 8267 | M89: 5 | N89: =Table1[[#This Row],[Discount]]/100 -> 0.05 | O89: 826.7 | P89: 15707.3 | Q89: 236 | R89: 15943.3 | S89: Wallet | T89: Mobile App | U89: Delivered | V89: 5 | W89: 5
A90: TNORD0089 | B90: TNCUST0094 | C90: 45882 | D90: Karur | E90: Karur | F90: Other | G90: 44 | H90: 26-35 | I90: Beauty | J90: Shampoo | K90: 5 | L90: 3555 | M90: 20 | N90: =Table1[[#This Row],[Discount]]/100 -> 0.2 | O90: 3555 | P90: 14220 | Q90: 62 | R90: 14282 | S90: Cash on Delivery | T90: Marketplace | U90: Processing
A91: TNORD0090 | B91: TNCUST0129 | C91: 45883 | D91: Salem | E91: Salem | F91: Other | G91: 36 | H91: 46-55 | I91: Sports | J91: Running Shoes | K91: 2 | L91: 7241 | M91: 5 | N91: =Table1[[#This Row],[Discount]]/100 -> 0.05 | O91: 724.1 | P91: 13757.9 | Q91: 166 | R91: 13923.9 | S91: Credit Card | T91: Website | U91: Delivered | V91: 4 | W91: 4
A92: TNORD0091 | B92: TNCUST0196 | C92: 45721 | D92: Nagercoil | E92: Kanyakumari | F92: Male | G92: 23 | H92: 36-45 | I92: Beauty | J92: Shampoo | K92: 3 | L92: 2421 | M92: 25 | N92: =Table1[[#This Row],[Discount]]/100 -> 0.25 | O92: 1815.75 | P92: 5447.25 | Q92: 237 | R92: 5684.25 | S92: Cash on Delivery | T92: Marketplace | U92: Processing
A93: TNORD0092 | B93: TNCUST0082 | C93: 45699 | D93: Madurai | E93: Madurai | F93: Male | G93: 32 | H93: 36-45 | I93: Grocery | J93: Rice | K93: 2 | L93: 1779 | M93: 20 | N93: =Table1[[#This Row],[Discount]]/100 -> 0.2 | O93: 711.6 | P93: 2846.4 | Q93: 118 | R93: 2964.4 | S93: Credit Card | T93: Website | U93: Delivered | V93: 3 | W93: 3
A94: TNORD0093 | B94: TNCUST0029 | C94: 45969 | D94: Chennai | E94: Chennai | F94: Female | G94: 45 | H94: 26-35 | I94: Home & Kitchen | J94: Water Bottle | K94: 2 | L94: 386 | M94: 5 | N94: =Table1[[#This Row],[Discount]]/100 -> 0.05 | O94: 38.6 | P94: 733.4 | Q94: 160 | R94: 893.4 | S94: Debit Card | T94: Website | U94: Processing
A95: TNORD0094 | B95: TNCUST0075 | C95: 45781 | D95: Chennai | E95: Chennai | F95: Female | G95: 27 | H95: 18-25 | I95: Fashion | J95: Jeans | K95: 5 | L95: 914 | M95: 0 | N95: =Table1[[#This Row],[Discount]]/100 -> 0 | O95: 0 | P95: 4570 | Q95: 167 | R95: 4737 | S95: Net Banking | T95: Mobile App | U95: Shipped | V95: 6
A96: TNORD0095 | B96: TNCUST0224 | C96: 45941 | D96: Tiruchirappalli | E96: Tiruchirappalli | F96: Female | G96: 42 | H96: 18-25 | I96: Beauty | J96: Sunscreen | K96: 2 | L96: 2304 | M96: 20 | N96: =Table1[[#This Row],[Discount]]/100 -> 0.2 | O96: 921.6 | P96: 3686.4 | Q96: 149 | R96: 3835.4 | S96: Wallet | T96: Mobile App | U96: Processing
A97: TNORD0096 | B97: TNCUST0087 | C97: 45680 | D97: Tirunelveli | E97: Tirunelveli | F97: Other | G97: 52 | H97: 26-35 | I97: Home & Kitchen | J97: Mixer Grinder | K97: 3 | L97: 4250 | M97: 25 | N97: =Table1[[#This Row],[Discount]]/100 -> 0.25 | O97: 3187.5 | P97: 9562.5 | Q97: 54 | R97: 9616.5 | S97: Wallet | T97: Mobile App | U97: Shipped | V97: 3
A98: TNORD0097 | B98: TNCUST0209 | C98: 45816 | D98: Hosur | E98: Krishnagiri | F98: Other | G98: 43 | H98: 46-55 | I98: Grocery | J98: Cooking Oil | K98: 2 | L98: 1281 | M98: 5 | N98: =Table1[[#This Row],[Discount]]/100 -> 0.05 | O98: 128.1 | P98: 2433.9 | Q98: 100 | R98: 2533.9 | S98: Debit Card | T98: Website | U98: Cancelled
A99: TNORD0098 | B99: TNCUST0128 | C99: 45883 | D99: Nagercoil | E99: Kanyakumari | F99: Other | G99: 39 | H99: 46-55 | I99: Sports | J99: Football | K99: 3 | L99: 6948 | M99: 10 | N99: =Table1[[#This Row],[Discount]]/100 -> 0.1 | O99: 2084.4 | P99: 18759.6 | Q99: 122 | R99: 18881.6 | S99: Debit Card | T99: Marketplace | U99: Delivered | V99: 4 | W99: 3.5
A100: TNORD0099 | B100: TNCUST0184 | C100: 45809 | D100: Salem | E100: Salem | F100: Female | G100: 46 | H100: 26-35 | I100: Electronics | J100: Smartwatch | K100: 1 | L100: 57240 | M100: 0 | N100: =Table1[[#This Row],[Discount]]/100 -> 0 | O100: 0 | P100: 57240 | Q100: 189 | R100: 57429 | S100: Wallet | T100: Mobile App | U100: Delivered | V100: 3 | W100: 4.5
...

Sheet DASHBOARD
A1: TAMIL NADU E-COMMERCE SALES DASHBOARD
A4: Sales Performance | Customer Insights | Order Analytics
A5: TOTAL SALES | D5: TOTAL ORDERS | G5: TOTAL QUANTITY | J5: AVERAGE RATING | P5: AVERAGE DELIVERY DAYS
A7: =GETPIVOTDATA("Total Sales",KPI!$B$1) -> 11906291 | D7: =GETPIVOTDATA("Total Orders",KPI!$B$1) -> 500 | G7: =GETPIVOTDATA("Total Quantity",KPI!$B$1) -> 1465 | J7: =GETPIVOTDATA("Average of Customer_Rating",KPI!$B$1) -> 4.0217391 | P7: =GETPIVOTDATA("Average of Delivery_Days",KPI!$B$1) -> 4.1066998

Sheet KPI
B1: Total Sales | C1: Total Orders | D1: Total Quantity | E1: Average of Customer_Rating | F1: Average of Delivery_Days
B2: 11906291 | C2: 500 | D2: 1465 | E2: 4.0217391 | F2: 4.1066998

Sheet MONTHLY SALES
B1: Row Labels | C1: Sum of Total_Amount_INR
B2: Jan | C2: 721624.45
B3: Feb | C3: 1053649.8
B4: Mar | C4: 969015.8
B5: Apr | C5: 1364396.9
B6: May | C6: 572779.65
B7: Jun | C7: 999373.4
B8: Jul | C8: 1005396.7
B9: Aug | C9: 855858.5
B10: Sep | C10: 1032071.7
B11: Oct | C11: 850444.8
B12: Nov | C12: 1413337.7
B13: Dec | C13: 1068341.3

Sheet SALES BY DISTRICT
B2: Row Labels | C2: Sum of Total_Amount_INR
B3: Thoothukudi | C3: 524669.45
B4: Thanjavur | C4: 563004.4
B5: Erode | C5: 586757.05
B6: Coimbatore | C6: 665104.4
B7: Karur | C7: 685587.4
B8: Madurai | C8: 750639.05
B9: Krishnagiri | C9: 783924.05
B10: Chennai | C10: 787029.5
B11: Vellore | C11: 793705.05
B12: Dindigul | C12: 851169.15
B13: Salem | C13: 889477.15
B14: Kanyakumari | C14: 905518.75
... B17: Tiruchirappalli | C17: 1109699.6

Sheet SALES BY CATEGORY
B2: Row Labels | C2: Sum of Total_Amount_INR
B3: Beauty | C3: 561426.65
B4: Electronics | C4: 8377695.1
B5: Fashion | C5: 714690.45
B6: Grocery | C6: 292016.4
B7: Home & Kitchen | C7: 889499.15
B8: Sports | C8: 1070963.1

Sheet ORDER STATUS
C2: Count of Order_ID
B3: Cancelled | C3: 25
B4: Delivered | C4: 322
B5: Processing | C5: 40
B6: Returned | C6: 32
B7: Shipped | C7: 81

Sheet PAYMENT METHOD
B2: Row Labels | C2: Count of Order_ID
B3: Cash on Delivery | C3: 87
B4: Credit Card | C4: 77
B5: Debit Card | C5: 80
B6: Net Banking | C6: 72
B7: UPI | C7: 100
B8: Wallet | C8: 84

Sheet SALES CHANNEL
B2: Row Labels | C2: Sum of Total_Amount_INR
B3: Marketplace | C3: 3883322.4
B4: Mobile App | C4: 4864974.1
B5: Website | C5: 3157994.4

Sheet TOP PRODUCTS
B2: Row Labels | C2: Sum of Total_Amount_INR
B3: Smartphone | C3: 2355279.4
B4: Laptop | C4: 1852230.4
B5: Headphones | C5: 1596624.6
B6: Smartwatch | C6: 1373061.2
B7: Power Bank | C7: 1200499.4
B8: Football | C8: 311284.95
B9: Badminton Racket | C9: 256863.35
B10: Mixer Grinder | C10: 242258.15
B11: Cookware Set | C11: 238310.8
B12: Jeans | C12: 202676.8
